CellChip/CellChip.py
CellChip/CellChip_argument.py
CellChip/__init__.py
CellChip/extension/__init__.py
CellChip/extension/custom_SpaGCN.py
CellChip/model/__init__.py
CellChip/model/model.py
CellChip/model/ot_model.py
CellChip/plotting/__init__.py
CellChip/plotting/plot.py
CellChip/utilities/__init__.py
CellChip/utilities/util.py
Polyomino/Polyomino.py
Polyomino/Polyomino_argument.py
Polyomino/__init__.py
Polyomino/extension/__init__.py
Polyomino/extension/custom_SpaGCN.py
Polyomino/model/__init__.py
Polyomino/model/model.py
Polyomino/model/ot_model.py
Polyomino/plotting/__init__.py
Polyomino/plotting/plot.py
Polyomino/utilities/__init__.py
Polyomino/utilities/util.py
Zmap/Zmap.py
Zmap/Zmap_argument.py
Zmap/__init__.py
Zmap/extension/__init__.py
Zmap/extension/custom_SpaGCN.py
Zmap/model/__init__.py
Zmap/model/model.py
Zmap/model/ot_model.py
Zmap/plotting/__init__.py
Zmap/plotting/plot.py
Zmap/utilities/__init__.py
Zmap/utilities/util.py
Zmap_sc-1.0.1.dist-info/LICENSE
Zmap_sc-1.0.1.dist-info/METADATA
Zmap_sc-1.0.1.dist-info/WHEEL
Zmap_sc-1.0.1.dist-info/entry_points.txt
Zmap_sc-1.0.1.dist-info/top_level.txt
Zmap_sc-1.0.1.dist-info/RECORD
