Metadata-Version: 2.1
Name: Zmap-sc
Version: 1.0.1
Summary: An algorithm framework employing multi-layered regional constraints to accurately assign cell locations, enhancing spatial accuracy and resilience to noise.
Home-page: https://github.com/caiquanyou/Zmap
Author: Cai Quanyou
Author-email: cai_quanyou@gibh.ac.cn
License: UNKNOWN
Platform: UNKNOWN
Classifier: Programming Language :: Python :: 3.8
Classifier: Operating System :: MacOS
Requires-Python: >=3.8.0
Requires-Dist: lap (>=0.4.0)
Requires-Dist: scikit-learn (>=1.1.3)
Requires-Dist: numpydoc (>=1.1)
Requires-Dist: anndata (>=0.8.0)
Requires-Dist: scanpy (>=1.9.1)
Requires-Dist: scipy (>=1.9.3)
Requires-Dist: numba (>=0.14.0)
Requires-Dist: tqdm (>=4.66.5)
Requires-Dist: igraph (>=0.11.6)
Requires-Dist: leidenalg (>=0.10.2)
